preppipe/__init__.py
preppipe/_version.py
preppipe/commontypes.py
preppipe/exceptions.py
preppipe/exportcache.py
preppipe/imageexpr.py
preppipe/inputmodel.py
preppipe/irbase.py
preppipe/irdataop.py
preppipe/language.py
preppipe/nameresolution.py
preppipe/pipeline.py
preppipe/pipeline_cmd.py
preppipe/testbench.py
preppipe/tooldecl.py
preppipe/valueexpr.py
preppipe/vnmodel.py
preppipe/__pyinstaller/__init__.py
preppipe/__pyinstaller/hook-preppipe.py
preppipe/analysis/__init__.py
preppipe/analysis/icfg.py
preppipe/analysis/passes.py
preppipe/analysis/vnmodel/__init__.py
preppipe/analysis/vnmodel/assetusage.py
preppipe/analysis/vnmodel/passes.py
preppipe/analysis/vnmodel/timemodel.py
preppipe/analysis/vnmodel/vnsaydump.py
preppipe/assets/__init__.py
preppipe/assets/assetclassdecl.py
preppipe/assets/assetmanager.py
preppipe/assets/assetmanager_cmd.py
preppipe/assets/fileasset.py
preppipe/assets/imports.py
preppipe/assets/init_builtins.py
preppipe/assets/_install/GENERATED_FILES_ONLY_DO_NOT_PUT_SOURCES_HERE
preppipe/enginecommon/__init__.py
preppipe/enginecommon/ast.py
preppipe/enginecommon/codegen.py
preppipe/enginecommon/export.py
preppipe/frontend/CommandParse.g4
preppipe/frontend/CommandScan.g4
preppipe/frontend/Makefile
preppipe/frontend/__init__.py
preppipe/frontend/commanddocs.py
preppipe/frontend/commandsemantics.py
preppipe/frontend/commandsyntaxparser.py
preppipe/frontend/docx.py
preppipe/frontend/markdown.py
preppipe/frontend/opendocument.py
preppipe/frontend/text.py
preppipe/frontend/_antlr_generated/CommandParseLexer.py
preppipe/frontend/_antlr_generated/CommandParseListener.py
preppipe/frontend/_antlr_generated/CommandParseParser.py
preppipe/frontend/_antlr_generated/CommandParseVisitor.py
preppipe/frontend/_antlr_generated/CommandScanLexer.py
preppipe/frontend/_antlr_generated/CommandScanListener.py
preppipe/frontend/_antlr_generated/CommandScanParser.py
preppipe/frontend/_antlr_generated/README.txt
preppipe/frontend/_antlr_generated/__init__.py
preppipe-0.0.1.post269.dist-info/LICENSE
preppipe-0.0.1.post269.dist-info/METADATA
preppipe-0.0.1.post269.dist-info/WHEEL
preppipe-0.0.1.post269.dist-info/entry_points.txt
preppipe-0.0.1.post269.dist-info/top_level.txt
preppipe-0.0.1.post269.dist-info/RECORD
