Metadata-Version: 2.1
Name: preppipe
Version: 0.0.1.post269
Summary: Document to Visual Novel project generator
Home-page: https://github.com/PrepPipe/preppipe-python
Author: Shengjie Xu
Author-email: xsj617603321@gmail.com
License: Apache-2.0
Project-URL: Bug Tracker, https://github.com/PrepPipe/preppipe-python/issues
Classifier: Programming Language :: Python :: 3
Classifier: License :: OSI Approved :: Apache Software License
Classifier: Operating System :: OS Independent
Classifier: Development Status :: 3 - Alpha
Requires-Python: >=3.10
License-File: LICENSE
Requires-Dist: llist
Requires-Dist: odfpy
Requires-Dist: python-docx
Requires-Dist: chardet
Requires-Dist: marko
Requires-Dist: pyyaml
Requires-Dist: pillow
Requires-Dist: pydub
Requires-Dist: numpy
Requires-Dist: scipy
Requires-Dist: matplotlib
Requires-Dist: opencv-python
Requires-Dist: editdistance
Requires-Dist: bidict
Requires-Dist: pypinyin
Requires-Dist: graphviz
Requires-Dist: pathvalidate
Requires-Dist: xlsxwriter
Requires-Dist: psd-tools
Requires-Dist: antlr4-python3-runtime<4.11.0,>=4.10
Provides-Extra: gui
Requires-Dist: tkinterdnd2; extra == "gui"
